{
  "id": "CMG_CSM.C05_External_Cardiac_Pacing__Zoll_X_Series_",
  "cmg_number": "CSM.C05",
  "title": "External Cardiac Pacing (Zoll X Series)",
  "version_date": null,
  "section": "Clinical Skill",
  "content_markdown": "#### Indications\n- Bradycardia with poor perfusion. \n\n#### Procedure\n\n- Ensure chest leads are positioned well off the chest. \n- Remove CPR feedback pad from the posterior pad (red rectangle) (see **Figure 1**).\n\nFigure 1\n\n- Place posterior pad vertically beneath scapula, along left vertebral edge (see **Figure 2**).\n\nFigure 2\n\nFigure 3\n\n- Place anterior pad (purple circle) horizontally in V2/V3 position (see **Figure 3**).\n\n- Place CPR feedback pad in centre of the chest on the sternum. \n- Attach pads to pads cable.\n\n- Push Green PACER button.\n\n- Select [PACER RATE] to at least 50% above the patient’s intrinsic rate.\n\n- Select [PACER OUTPUT] and reduce to 10mA.\n\n- Select [START PACING].\n\n- Ensure pacing markers are visible on ECG.\n\n- Slowly increase electrical current by 10mA increments until electrical and mechanical capture are achieved.\n\n- Once electrical and mechanical capture are obtained (change in QRS morphology and pacing markers synchronised with each QRS complex) increase out by a further 10mA and then decrease by 5mA.\n\n- Confirm capture with manual pulse rate and BP.\n\n- Provide analgesia (morphine/ fentanyl/ midazolam) if required.\n\n#### Contraindications\n- Nil when indicated.\n\n#### Complications\n- Pain – provide reassurance and appropriate pain relief (morphine/fentanyl/midazolam).\n- Failure to capture due to resistance or unknown reason.\n\n#### Specific Notes\n- External cardiac pacing is preferred over adrenaline infusion for bradycardia post cardiac arrest.\n- If IV access in situ, Adrenaline infusion must also be prepared for use in event of pacing failure.",
  "is_icp_only": true,
  "dose_lookup": {
    "Morphine": [
      {
        "text": "Morphine: 2.5mg – 5mg SC",
        "dose_values": [
          {
            "amount": "2.5",
            "unit": "mg"
          },
          {
            "amount": "5",
            "unit": "mg"
          }
        ]
      },
      {
        "text": "Morphine: 10mg IV or SC Midazolam: 5mg IV or 10mg SC. Repeat @10/60 (max. dose 60mg) ",
        "dose_values": [
          {
            "amount": "10",
            "unit": "mg"
          },
          {
            "amount": "5",
            "unit": "mg"
          },
          {
            "amount": "10",
            "unit": "mg"
          },
          {
            "amount": "60",
            "unit": "mg"
          }
        ]
      },
      {
        "text": "Calculated dose of morphine above 10 mg Doses above 10 mg are rarely required.",
        "dose_values": [
          {
            "amount": "10",
            "unit": "mg"
          },
          {
            "amount": "10",
            "unit": "mg"
          }
        ]
      },
      {
        "text": "Calculated dose of morphine above 20 mg",
        "dose_values": [
          {
            "amount": "20",
            "unit": "mg"
          }
        ]
      },
      {
        "text": "0.05mg/kg IV/IO over 60 seconds. ",
        "dose_values": [
          {
            "amount": "0.05",
            "unit": "mg"
          }
        ]
      },
      {
        "text": "IV/IO morphine may be administered to patients with mild-moderate hypotension (sBP 70 – 90mmHg) 0.025mg/kg IV/IO over 60 seconds. ",
        "dose_values": [
          {
            "amount": "0.025",
            "unit": "mg"
          }
        ]
      },
      {
        "text": " Withdraw 29mL from 50mL NaCl bag, then add 3mL (30mg) morphine and 6mL (30mg) midazolam to make 30mg:30mg/30mL",
        "dose_values": [
          {
            "amount": "29",
            "unit": "mL"
          },
          {
            "amount": "50",
            "unit": "mL"
          },
          {
            "amount": "3",
            "unit": "mL"
          },
          {
            "amount": "30",
            "unit": "mg"
          },
          {
            "amount": "6",
            "unit": "mL"
          },
          {
            "amount": "30",
            "unit": "mg"
          },
          {
            "amount": "30",
            "unit": "mg"
          },
          {
            "amount": "30",
            "unit": "mg"
          },
          {
            "amount": "30",
            "unit": "mL"
          }
        ]
      },
      {
        "text": "Morphine: IM (Max 2 Doses)",
        "dose_values": []
      },
      {
        "text": "Morphine: IV (To a total of 20mg)",
        "dose_values": [
          {
            "amount": "20",
            "unit": "mg"
          }
        ]
      },
      {
        "text": " Consider: Adjunct 0.05mg/kg bolus of morphine for patients with severely painful injuries to achieve adequate analgesia. ",
        "dose_values": [
          {
            "amount": "0.05",
            "unit": "mg"
          }
        ]
      },
      {
        "text": " Withdraw 29mL from 50mL NaCl bag, then add 6mL (30mg) midazolam and 3mL (30mg) morphine to make 30mg:30mg/30mL",
        "dose_values": [
          {
            "amount": "29",
            "unit": "mL"
          },
          {
            "amount": "50",
            "unit": "mL"
          },
          {
            "amount": "6",
            "unit": "mL"
          },
          {
            "amount": "30",
            "unit": "mg"
          },
          {
            "amount": "3",
            "unit": "mL"
          },
          {
            "amount": "30",
            "unit": "mg"
          },
          {
            "amount": "30",
            "unit": "mg"
          },
          {
            "amount": "30",
            "unit": "mg"
          },
          {
            "amount": "30",
            "unit": "mL"
          }
        ]
      },
      {
        "text": "Repeat @10/60 if requires (max. 60mg)",
        "dose_values": [
          {
            "amount": "60",
            "unit": "mg"
          }
        ]
      },
      {
        "text": ". If dilution of the drug is required, open the normal saline ampoule or insert the needle and syringe into the injection port of a bag of saline. Draw back on the syringe and draw up the required amount of fluid for dilution of the drug (i.e. 9mls of normal saline with 1ml of Morphine Sulphate for a total volume of 10mls).",
        "dose_values": [
          {
            "amount": "1",
            "unit": "ml"
          }
        ]
      },
      {
        "text": "##### Type\nOpioid analgesic [S8]\n\n##### Presentations\n10mg in 1ml – glass ampoule\n\n##### Actions\n\n- Analgesia\n\n- Anxiolytic\n\n- Vasodilation\n\n##### Pharmacokinetics\n**IV**\n Onset: 5 - 10 minutes\n Max Effect: 20 minutes\n Duration: 4 - 5 hours\n\n**IM**\n Onset: 10 - 30 minutes\n Max Effect: 30 minutes\n Duration: 4 - 5 hours\n\n#### Uses\n\n- Analgesia for moderate to severe pain\n\n- Maintain analgosedation in intubated patients in conjunction with midazolam.\n\n- Reduce dyspnoea in palliative care patients.\n\n- Relieve suffering due to terminal palliative care emergencies (no active treatment).\n\n#### Adverse Effects\n\n- Nausea and vomiting\n\n- Altered level of consciousness\n\n- Respiratory depression\n\n- Hypotension\n\n- Bradycardia\n\n#### Contraindications\n\n- Respiratory depression\n\n- Systolic blood pressure Disregard contraindications when managing palliative care emergencies (no active treatment) patients.\n\n#### Precautions\n\n- GCS ≤13\n\n- Known hypersensitivity\n\n- Frail patients\n\n- COPD patients\n\n- Hypovolaemic patients\n\n- Systolic BP 70 – 90mmHg (see below)\n\n- Children **AP:** max. total dose 20mg\n- **ICP:** no max. total dose\n- Consider IM: \n- IV/IO unobtainable\n- Little risk of hypotension- Patient contact estimated >20/60- No ischaemic chest pain- 0.1mg/kg IM \n- Repeat once @30/60 if required\n- **AP:** max. total dose 20mg##### Adults only\nIV/IO morphine may be administered to patients with mild-moderate hypotension (sBP 70 – 90mmHg)\n\n- 0.025mg/kg IV/IO over 60 seconds. \n- Repeat @10/60 as required.\n- Do not repeat if sBP drops ≥10mmHg, even if it remains above 70mmHg. \n- **AP:** max. total dose 20mg- **ICP:** no max. total dose#### Post-intubation analgosedation (as adjunct to midazolam)##### Adult (infusion pump)\n**Note:** Withdraw 29mL from 50mL NaCl bag, then add 3mL (30mg) morphine and 6mL (30mg) midazolam to make 30mg:30mg/30mL\n\n- **ICP: **Initial infusion rate: 5mg/hr \n- Lower soft infusion limit: 1mg/hr\n- Upper soft infusion limit: 30mg/hr\n- Upper hard infusion limit: 50mg/hr- **ICP: **Default bolus: 2mg (2mL) \n- Lower hard bolus limit: 0.5mg (0.5mL)\n- Upper hard bolus limit: 5mg (5mL)#### Palliative care\n**Note:** Always refer to and follow patient specific treatment plan when available.\n##### Adult with dyspnoea\n- 2.5 - 5mg SC/IM/IV\nConsider patient weight when selecting dose\n##### Adult with distressing pain\n- Refer to Palliative Care Medication Calculator\n##### Adult with terminal palliative care emergency\n- SC/IM/IV: 10mg\nIn conjunction with midazolam\n##### Paediatric\nRefer to patient specific treatment plan for all palliative care presentations.",
        "dose_values": [
          {
            "amount": "10",
            "unit": "mg"
          },
          {
            "amount": "1",
            "unit": "ml"
          },
          {
            "amount": "20",
            "unit": "mg"
          },
          {
            "amount": "0.1",
            "unit": "mg"
          },
          {
            "amount": "20",
            "unit": "mg"
          },
          {
            "amount": "0.025",
            "unit": "mg"
          },
          {
            "amount": "20",
            "unit": "mg"
          },
          {
            "amount": "29",
            "unit": "mL"
          },
          {
            "amount": "50",
            "unit": "mL"
          },
          {
            "amount": "3",
            "unit": "mL"
          },
          {
            "amount": "30",
            "unit": "mg"
          },
          {
            "amount": "6",
            "unit": "mL"
          },
          {
            "amount": "30",
            "unit": "mg"
          },
          {
            "amount": "30",
            "unit": "mg"
          },
          {
            "amount": "30",
            "unit": "mg"
          },
          {
            "amount": "30",
            "unit": "mL"
          },
          {
            "amount": "5",
            "unit": "mg"
          },
          {
            "amount": "1",
            "unit": "mg"
          },
          {
            "amount": "30",
            "unit": "mg"
          },
          {
            "amount": "50",
            "unit": "mg"
          },
          {
            "amount": "2",
            "unit": "mg"
          },
          {
            "amount": "2",
            "unit": "mL"
          },
          {
            "amount": "0.5",
            "unit": "mg"
          },
          {
            "amount": "0.5",
            "unit": "mL"
          },
          {
            "amount": "5",
            "unit": "mg"
          },
          {
            "amount": "5",
            "unit": "mL"
          },
          {
            "amount": "5",
            "unit": "mg"
          },
          {
            "amount": "10",
            "unit": "mg"
          }
        ],
        "source": "app-morphine-sulphate"
      }
    ],
    "Midazolam": [
      {
        "text": "Midazolam: 2.5mg – 5mg SC",
        "dose_values": [
          {
            "amount": "2.5",
            "unit": "mg"
          },
          {
            "amount": "5",
            "unit": "mg"
          }
        ]
      },
      {
        "text": "Morphine: 10mg IV or SC Midazolam: 5mg IV or 10mg SC. Repeat @10/60 (max. dose 60mg) ",
        "dose_values": [
          {
            "amount": "10",
            "unit": "mg"
          },
          {
            "amount": "5",
            "unit": "mg"
          },
          {
            "amount": "10",
            "unit": "mg"
          },
          {
            "amount": "60",
            "unit": "mg"
          }
        ]
      },
      {
        "text": "Formula: 1.5mg/kg Preparation: 150mg in 3mls Dose: 52.5mg Volume: 1ml Midazolam (dilute to 1mg/ml): Formula: 0.05mg/kg Preparation: 5mg in 5mls Dose: 1.75mg Volume: 1.75ml",
        "dose_values": [
          {
            "amount": "1.5",
            "unit": "mg"
          },
          {
            "amount": "150",
            "unit": "mg"
          },
          {
            "amount": "52.5",
            "unit": "mg"
          },
          {
            "amount": "1",
            "unit": "ml"
          },
          {
            "amount": "1",
            "unit": "mg"
          },
          {
            "amount": "0.05",
            "unit": "mg"
          },
          {
            "amount": "5",
            "unit": "mg"
          },
          {
            "amount": "1.75",
            "unit": "mg"
          },
          {
            "amount": "1.75",
            "unit": "ml"
          }
        ]
      },
      {
        "text": "Preparation: 150mg in 3mls Dose: 60mg Volume: 1.2ml Midazolam (dilute to 1mg/ml): Formula: 0.05mg/kg Preparation: 5mg in 5mls Dose: 2mg Volume: 2ml",
        "dose_values": [
          {
            "amount": "150",
            "unit": "mg"
          },
          {
            "amount": "60",
            "unit": "mg"
          },
          {
            "amount": "1.2",
            "unit": "ml"
          },
          {
            "amount": "1",
            "unit": "mg"
          },
          {
            "amount": "0.05",
            "unit": "mg"
          },
          {
            "amount": "5",
            "unit": "mg"
          },
          {
            "amount": "2",
            "unit": "mg"
          },
          {
            "amount": "2",
            "unit": "ml"
          }
        ]
      },
      {
        "text": "Formula: 1.5mg/kg Preparation: 150mg in 3mls Dose: 67.5mg Volume: 1.3ml Midazolam (dilute to 1mg/ml): Formula: 0.05mg/kg Preparation: 5mg in 5mls Dose: 2.25mg Volume: 2.25ml",
        "dose_values": [
          {
            "amount": "1.5",
            "unit": "mg"
          },
          {
            "amount": "150",
            "unit": "mg"
          },
          {
            "amount": "67.5",
            "unit": "mg"
          },
          {
            "amount": "1.3",
            "unit": "ml"
          },
          {
            "amount": "1",
            "unit": "mg"
          },
          {
            "amount": "0.05",
            "unit": "mg"
          },
          {
            "amount": "5",
            "unit": "mg"
          },
          {
            "amount": "2.25",
            "unit": "mg"
          },
          {
            "amount": "2.25",
            "unit": "ml"
          }
        ]
      },
      {
        "text": "Formula: 1.5mg/kg Preparation: 150mg in 3mls Dose: 75mg Volume: 1.5ml Midazolam (dilute to 1mg/ml): Formula: 0.05mg/kg Preparation: 5mg in 5mls Dose: 2.5mg Volume: 2.5ml",
        "dose_values": [
          {
            "amount": "1.5",
            "unit": "mg"
          },
          {
            "amount": "150",
            "unit": "mg"
          },
          {
            "amount": "75",
            "unit": "mg"
          },
          {
            "amount": "1.5",
            "unit": "ml"
          },
          {
            "amount": "1",
            "unit": "mg"
          },
          {
            "amount": "0.05",
            "unit": "mg"
          },
          {
            "amount": "5",
            "unit": "mg"
          },
          {
            "amount": "2.5",
            "unit": "mg"
          },
          {
            "amount": "2.5",
            "unit": "ml"
          }
        ]
      },
      {
        "text": "Formula: 1.5mg/kg Preparation: 150mg in 3mls Dose: 90mg Volume: 1.8ml Midazolam (dilute to 1mg/ml): Formula: 0.05mg/kg Preparation: 5mg in 5mls Dose: 3mg Volume: 3ml",
        "dose_values": [
          {
            "amount": "1.5",
            "unit": "mg"
          },
          {
            "amount": "150",
            "unit": "mg"
          },
          {
            "amount": "90",
            "unit": "mg"
          },
          {
            "amount": "1.8",
            "unit": "ml"
          },
          {
            "amount": "1",
            "unit": "mg"
          },
          {
            "amount": "0.05",
            "unit": "mg"
          },
          {
            "amount": "5",
            "unit": "mg"
          },
          {
            "amount": "3",
            "unit": "mg"
          },
          {
            "amount": "3",
            "unit": "ml"
          }
        ]
      },
      {
        "text": "Formula: 1.5mg/kg Preparation: 150mg in 3mls Dose: 105mg Volume: 2.1ml Midazolam (dilute to 1mg/ml): Formula: 0.05mg/kg Preparation: 5mg in 5mls Dose: 3.5mg Volume: 3.5ml",
        "dose_values": [
          {
            "amount": "1.5",
            "unit": "mg"
          },
          {
            "amount": "150",
            "unit": "mg"
          },
          {
            "amount": "105",
            "unit": "mg"
          },
          {
            "amount": "2.1",
            "unit": "ml"
          },
          {
            "amount": "1",
            "unit": "mg"
          },
          {
            "amount": "0.05",
            "unit": "mg"
          },
          {
            "amount": "5",
            "unit": "mg"
          },
          {
            "amount": "3.5",
            "unit": "mg"
          },
          {
            "amount": "3.5",
            "unit": "ml"
          }
        ]
      },
      {
        "text": "Formula: 1.5mg/kg Preparation: 150mg in 3mls Dose: 120mg Volume: 2.4ml Midazolam (dilute to 1mg/ml): Formula: 0.05mg/kg Preparation: 5mg in 5mls Dose: 4mg Volume: 4ml",
        "dose_values": [
          {
            "amount": "1.5",
            "unit": "mg"
          },
          {
            "amount": "150",
            "unit": "mg"
          },
          {
            "amount": "120",
            "unit": "mg"
          },
          {
            "amount": "2.4",
            "unit": "ml"
          },
          {
            "amount": "1",
            "unit": "mg"
          },
          {
            "amount": "0.05",
            "unit": "mg"
          },
          {
            "amount": "5",
            "unit": "mg"
          },
          {
            "amount": "4",
            "unit": "mg"
          },
          {
            "amount": "4",
            "unit": "ml"
          }
        ]
      },
      {
        "text": "Formula: 1.5mg/kg Preparation: 150mg in 3mls Dose: 135mg Volume: 2.7ml Midazolam (dilute to 1mg/ml): Formula: 0.05mg/kg Preparation: 5mg in 5mls Dose: 4.5mg Volume: 4.5ml",
        "dose_values": [
          {
            "amount": "1.5",
            "unit": "mg"
          },
          {
            "amount": "150",
            "unit": "mg"
          },
          {
            "amount": "135",
            "unit": "mg"
          },
          {
            "amount": "2.7",
            "unit": "ml"
          },
          {
            "amount": "1",
            "unit": "mg"
          },
          {
            "amount": "0.05",
            "unit": "mg"
          },
          {
            "amount": "5",
            "unit": "mg"
          },
          {
            "amount": "4.5",
            "unit": "mg"
          },
          {
            "amount": "4.5",
            "unit": "ml"
          }
        ]
      },
      {
        "text": "Formula: 1.5mg/kg Preparation: 150mg in 3mls Dose: 150mg Volume: 3ml Midazolam (dilute to 1mg/ml): Formula: 0.05mg/kg Preparation: 5mg in 5mls Dose: 5mg Volume: 5ml",
        "dose_values": [
          {
            "amount": "1.5",
            "unit": "mg"
          },
          {
            "amount": "150",
            "unit": "mg"
          },
          {
            "amount": "150",
            "unit": "mg"
          },
          {
            "amount": "3",
            "unit": "ml"
          },
          {
            "amount": "1",
            "unit": "mg"
          },
          {
            "amount": "0.05",
            "unit": "mg"
          },
          {
            "amount": "5",
            "unit": "mg"
          },
          {
            "amount": "5",
            "unit": "mg"
          },
          {
            "amount": "5",
            "unit": "ml"
          }
        ]
      },
      {
        "text": "Formula: 1.5mg/kg Preparation: 150mg in 3mls Dose: 150mg Volume: 3ml Midazolam (dilute to 1mg/ml): Formula: 0.05mg/kg Preparation: 5mg in 5mls Dose: 5.5mg Volume: 5.5ml",
        "dose_values": [
          {
            "amount": "1.5",
            "unit": "mg"
          },
          {
            "amount": "150",
            "unit": "mg"
          },
          {
            "amount": "150",
            "unit": "mg"
          },
          {
            "amount": "3",
            "unit": "ml"
          },
          {
            "amount": "1",
            "unit": "mg"
          },
          {
            "amount": "0.05",
            "unit": "mg"
          },
          {
            "amount": "5",
            "unit": "mg"
          },
          {
            "amount": "5.5",
            "unit": "mg"
          },
          {
            "amount": "5.5",
            "unit": "ml"
          }
        ]
      },
      {
        "text": "Formula: 1.5mg/kg Preparation: 150mg in 3mls Dose: 150mg Volume: 3ml Midazolam (dilute to 1mg/ml): Formula: 0.05mg/kg Preparation: 5mg in 5mls Dose: 6mg Volume: 6ml",
        "dose_values": [
          {
            "amount": "1.5",
            "unit": "mg"
          },
          {
            "amount": "150",
            "unit": "mg"
          },
          {
            "amount": "150",
            "unit": "mg"
          },
          {
            "amount": "3",
            "unit": "ml"
          },
          {
            "amount": "1",
            "unit": "mg"
          },
          {
            "amount": "0.05",
            "unit": "mg"
          },
          {
            "amount": "5",
            "unit": "mg"
          },
          {
            "amount": "6",
            "unit": "mg"
          },
          {
            "amount": "6",
            "unit": "ml"
          }
        ]
      },
      {
        "text": " Withdraw 29mL from 50mL NaCl bag, then add 3mL (30mg) morphine and 6mL (30mg) midazolam to make 30mg:30mg/30mL",
        "dose_values": [
          {
            "amount": "29",
            "unit": "mL"
          },
          {
            "amount": "50",
            "unit": "mL"
          },
          {
            "amount": "3",
            "unit": "mL"
          },
          {
            "amount": "30",
            "unit": "mg"
          },
          {
            "amount": "6",
            "unit": "mL"
          },
          {
            "amount": "30",
            "unit": "mg"
          },
          {
            "amount": "30",
            "unit": "mg"
          },
          {
            "amount": "30",
            "unit": "mg"
          },
          {
            "amount": "30",
            "unit": "mL"
          }
        ]
      },
      {
        "text": " Up to 4mg/kg IM injection",
        "dose_values": [
          {
            "amount": "4",
            "unit": "mg"
          }
        ]
      },
      {
        "text": " Consider: Adjunct 0.05mg/kg boluses of midazolam with ketamine infusions/boluses to achieve adequate sedation.",
        "dose_values": [
          {
            "amount": "0.05",
            "unit": "mg"
          }
        ]
      },
      {
        "text": "It is permissible to concurrently administer Midazolam and Levetiracetam if a seizure has persisted ≥20/60 without any pharmacological management prior to ACTAS arrival.",
        "dose_values": []
      },
      {
        "text": "If patient has previously had an unpleasant (fearful) experience with adenosine, consider a pre-dose of midazolam 1 – 1.5mg IV.",
        "dose_values": [
          {
            "amount": "1.5",
            "unit": "mg"
          }
        ]
      },
      {
        "text": "0.2mg/kg IM (max. 10mg) ",
        "dose_values": [
          {
            "amount": "0.2",
            "unit": "mg"
          },
          {
            "amount": "10",
            "unit": "mg"
          }
        ]
      },
      {
        "text": " Withdraw 29mL from 50mL NaCl bag, then add 6mL (30mg) midazolam and 3mL (30mg) morphine to make 30mg:30mg/30mL",
        "dose_values": [
          {
            "amount": "29",
            "unit": "mL"
          },
          {
            "amount": "50",
            "unit": "mL"
          },
          {
            "amount": "6",
            "unit": "mL"
          },
          {
            "amount": "30",
            "unit": "mg"
          },
          {
            "amount": "3",
            "unit": "mL"
          },
          {
            "amount": "30",
            "unit": "mg"
          },
          {
            "amount": "30",
            "unit": "mg"
          },
          {
            "amount": "30",
            "unit": "mg"
          },
          {
            "amount": "30",
            "unit": "mL"
          }
        ]
      },
      {
        "text": "##### Type\nBenzodiazepine \n\n##### Presentations\n15mg in 3mL ampoule\n\n##### Actions\n\n- Antiepileptic\n\n- Sedative\n\n- Anxiolytic\n\n- Amnesic\n\n##### Pharmacokinetics\n**IV/IO**\n Onset: 2 minutes\n Max Effect: 3 - 5 minutes\n Duration: 7 - 75 minutes\n\n**IM**\n Onset: 5 - 15 minutes\n Max Effect: 30 - 60 minutes\n Duration: 2 - 6 hours\n\n#### Uses\n\n- Status epilepticus\n\n- Post intubation analgosedation in conjunction with morphine\n\n- Relieve distress or restlessness in the palliative care patient\n\n- Relieve suffering due to terminal palliative care emergencies (no active treatment)\n\n#### Adverse Effects\n\n- Hypotension\nMore common when administer via fast IV push\n\n- Respiratory depression and loss of airway\nMore common at high doses or when synergising with other CNS depressant substances\n\n#### Contraindications\n\n- Previous allergic reaction to Midazolam\n\n#### Precautions\n\n- Hepatic failure\n\n- Frail or elderly\n\n- Known or suspected concurrent CNS depressant use\n\n- Known or suspected haemodynamic compromise\n\n#### Pregnancy and Breastfeeding##### Pregnancy\n- **Approved** for administration in ACTAS setting.\n\n##### Breastfeeding\n- **Approved** for administration in ACTAS setting.\n\n#### Doses#### Status Epilepticus##### Adult and Paediatric\n- 0.2mg/kg IM (max. 10mg) \n- Repeat @5/60 if required. (max. 2 doses)\n\n- **ICP:** 0.2mg/kg IV/IO push over 60 sec. (max. 10mg) \n- Repeat @5/60 if required. (max. 2 doses)\n#### Post Intubation Sedation (as adjunct to ketamine)##### Adult and Paediatric\n- **ICP:** 0.05mg/kg IV/IO push over 60 sec. \n- Repeat @5/60 as required.\n\n#### Post Intubation Sedation (as adjunct to morphine)##### Adult\n**Note:** Withdraw 29mL from 50mL NaCl bag, then add 6mL (30mg) midazolam and 3mL (30mg) morphine to make 30mg:30mg/30mL\n\n- **ICP:** Initial infusion rate: 5mg/hr \n- Lower soft infusion limit: 1mg/hr\n- Upper soft infusion limit: 30mg/hr\n- Upper hard infusion limit: 50mg/hr- **ICP:** Default bolus: 2mg (2mL) \n- Lower hard bolus limit: 0.5mg (0.5mL)\n- Upper hard bolus limit: 5mg (5mL)#### Palliative Care\n**Note:** Always refer to and follow patient specific treatment plan when available.\n##### Adult with distress or restlessness\n- 2.5 – 5mg SC/IM\nConsider patient weight when selecting dose\n##### Adult with terminal palliative care emergency\n- 5mg SC/IM/IV\nIn conjunction with morphine\n- Repeat @10/60 if requires (max. 60mg)\n\n##### Paediatric\nRefer to patient specific treatment plan for all palliative care presentations.",
        "dose_values": [
          {
            "amount": "15",
            "unit": "mg"
          },
          {
            "amount": "3",
            "unit": "mL"
          },
          {
            "amount": "0.2",
            "unit": "mg"
          },
          {
            "amount": "10",
            "unit": "mg"
          },
          {
            "amount": "0.2",
            "unit": "mg"
          },
          {
            "amount": "10",
            "unit": "mg"
          },
          {
            "amount": "0.05",
            "unit": "mg"
          },
          {
            "amount": "29",
            "unit": "mL"
          },
          {
            "amount": "50",
            "unit": "mL"
          },
          {
            "amount": "6",
            "unit": "mL"
          },
          {
            "amount": "30",
            "unit": "mg"
          },
          {
            "amount": "3",
            "unit": "mL"
          },
          {
            "amount": "30",
            "unit": "mg"
          },
          {
            "amount": "30",
            "unit": "mg"
          },
          {
            "amount": "30",
            "unit": "mg"
          },
          {
            "amount": "30",
            "unit": "mL"
          },
          {
            "amount": "5",
            "unit": "mg"
          },
          {
            "amount": "1",
            "unit": "mg"
          },
          {
            "amount": "30",
            "unit": "mg"
          },
          {
            "amount": "50",
            "unit": "mg"
          },
          {
            "amount": "2",
            "unit": "mg"
          },
          {
            "amount": "2",
            "unit": "mL"
          },
          {
            "amount": "0.5",
            "unit": "mg"
          },
          {
            "amount": "0.5",
            "unit": "mL"
          },
          {
            "amount": "5",
            "unit": "mg"
          },
          {
            "amount": "5",
            "unit": "mL"
          },
          {
            "amount": "5",
            "unit": "mg"
          },
          {
            "amount": "5",
            "unit": "mg"
          },
          {
            "amount": "60",
            "unit": "mg"
          }
        ],
        "source": "app-midazolam"
      }
    ],
    "Adrenaline": [
      {
        "text": "Adrenaline (1:10,000): Formula: 0.01mg/kg Preparation: 1mg in 10mls Dose: 0.03mg Volume: 0.3ml Adrenaline (1:10,000) ETT: Formula: 0.02mg/kg Preparation: 1mg in 10mls Dose: 0.06mg Volume: 0.6ml",
        "dose_values": [
          {
            "amount": "0.01",
            "unit": "mg"
          },
          {
            "amount": "1",
            "unit": "mg"
          },
          {
            "amount": "0.03",
            "unit": "mg"
          },
          {
            "amount": "0.3",
            "unit": "ml"
          },
          {
            "amount": "0.02",
            "unit": "mg"
          },
          {
            "amount": "1",
            "unit": "mg"
          },
          {
            "amount": "0.06",
            "unit": "mg"
          },
          {
            "amount": "0.6",
            "unit": "ml"
          }
        ]
      },
      {
        "text": "Adrenaline (1:10,000) IV/ IO: Formula: 0.01mg/kg Preparation: 1mg in 10mls Dose: 0.05mg Volume: 0.5ml",
        "dose_values": [
          {
            "amount": "0.01",
            "unit": "mg"
          },
          {
            "amount": "1",
            "unit": "mg"
          },
          {
            "amount": "0.05",
            "unit": "mg"
          },
          {
            "amount": "0.5",
            "unit": "ml"
          }
        ]
      },
      {
        "text": "Adrenaline (1:10,000) IV/IO: Formula: 0.01mg/kg Preparation: 1mg in 10mls Dose: 0.07mg Volume: 0.7ml",
        "dose_values": [
          {
            "amount": "0.01",
            "unit": "mg"
          },
          {
            "amount": "1",
            "unit": "mg"
          },
          {
            "amount": "0.07",
            "unit": "mg"
          },
          {
            "amount": "0.7",
            "unit": "ml"
          }
        ]
      },
      {
        "text": "Adrenaline (1:10,000) IV/IO: Formula: 0.01mg/kg Preparation: 1mg in 10mls Dose: 0.11 Volume: 1.1mls",
        "dose_values": [
          {
            "amount": "0.01",
            "unit": "mg"
          },
          {
            "amount": "1",
            "unit": "mg"
          }
        ]
      },
      {
        "text": "Adrenaline (1:10,000): Formula: 0.01mg/kg Preparation: 1mg in 10mls Dose: 0.13mg Volume: 1.3ml",
        "dose_values": [
          {
            "amount": "0.01",
            "unit": "mg"
          },
          {
            "amount": "1",
            "unit": "mg"
          },
          {
            "amount": "0.13",
            "unit": "mg"
          },
          {
            "amount": "1.3",
            "unit": "ml"
          }
        ]
      },
      {
        "text": "Adrenaline (1:10,000): Formula: 0.01mg/kg Preparation: 1mg in 10mls Dose: 0.15mg Volume: 1.5mls",
        "dose_values": [
          {
            "amount": "0.01",
            "unit": "mg"
          },
          {
            "amount": "1",
            "unit": "mg"
          },
          {
            "amount": "0.15",
            "unit": "mg"
          }
        ]
      },
      {
        "text": "Adrenaline (1:10,000): Formula: 0.01mg/kg Preparation: 1mg in 10mls Dose: 0.17mg Volume: 1.7ml",
        "dose_values": [
          {
            "amount": "0.01",
            "unit": "mg"
          },
          {
            "amount": "1",
            "unit": "mg"
          },
          {
            "amount": "0.17",
            "unit": "mg"
          },
          {
            "amount": "1.7",
            "unit": "ml"
          }
        ]
      },
      {
        "text": "Adrenaline (1:10,000): Formula: 0.01mg/kg Preparation: 1mg in 10mls Dose: 0.19mg Volume: 1.9ml",
        "dose_values": [
          {
            "amount": "0.01",
            "unit": "mg"
          },
          {
            "amount": "1",
            "unit": "mg"
          },
          {
            "amount": "0.19",
            "unit": "mg"
          },
          {
            "amount": "1.9",
            "unit": "ml"
          }
        ]
      },
      {
        "text": "Adrenaline (1:10,000): Formula: 0.01mg/kg Preparation: 1mg in 10mls Dose: 0.21mg Volume: 2.1ml",
        "dose_values": [
          {
            "amount": "0.01",
            "unit": "mg"
          },
          {
            "amount": "1",
            "unit": "mg"
          },
          {
            "amount": "0.21",
            "unit": "mg"
          },
          {
            "amount": "2.1",
            "unit": "ml"
          }
        ]
      },
      {
        "text": "Adrenaline (1:10,000): Formula: 0.01mg/kg Preparation: 1mg in 10mls Dose: 0.23mg Volume: 2.3ml",
        "dose_values": [
          {
            "amount": "0.01",
            "unit": "mg"
          },
          {
            "amount": "1",
            "unit": "mg"
          },
          {
            "amount": "0.23",
            "unit": "mg"
          },
          {
            "amount": "2.3",
            "unit": "ml"
          }
        ]
      },
      {
        "text": "Adrenaline (1:10,000): Formula: 0.01mg/kg Preparation: 1mg in 10mls Dose: 0.25mg  Volume: 2.5ml",
        "dose_values": [
          {
            "amount": "0.01",
            "unit": "mg"
          },
          {
            "amount": "1",
            "unit": "mg"
          },
          {
            "amount": "0.25",
            "unit": "mg"
          },
          {
            "amount": "2.5",
            "unit": "ml"
          }
        ]
      },
      {
        "text": "Adrenaline (1:10,000): Formula: 0.01mg/kg Preparation: 1mg in 10mls Dose: 0.27mg Volume: 2.7ml",
        "dose_values": [
          {
            "amount": "0.01",
            "unit": "mg"
          },
          {
            "amount": "1",
            "unit": "mg"
          },
          {
            "amount": "0.27",
            "unit": "mg"
          },
          {
            "amount": "2.7",
            "unit": "ml"
          }
        ]
      },
      {
        "text": "Adrenaline (1:10,000): Formula: 0.01mg/kg Preparation: 1mg in 10mls Dose: 0.3mg Volume: 3ml",
        "dose_values": [
          {
            "amount": "0.01",
            "unit": "mg"
          },
          {
            "amount": "1",
            "unit": "mg"
          },
          {
            "amount": "0.3",
            "unit": "mg"
          },
          {
            "amount": "3",
            "unit": "ml"
          }
        ]
      },
      {
        "text": "Adrenaline (1:10,000): Formula: 0.01mg/kg Preparation: 1mg in 10mls Dose: 0.33mg Volume: 3.3ml",
        "dose_values": [
          {
            "amount": "0.01",
            "unit": "mg"
          },
          {
            "amount": "1",
            "unit": "mg"
          },
          {
            "amount": "0.33",
            "unit": "mg"
          },
          {
            "amount": "3.3",
            "unit": "ml"
          }
        ]
      },
      {
        "text": "Adrenaline (1:10,000): Formula: 0.01mg/kg Preparation: 1mg in 10mls Dose: 1mg Volume: 10ml",
        "dose_values": [
          {
            "amount": "0.01",
            "unit": "mg"
          },
          {
            "amount": "1",
            "unit": "mg"
          },
          {
            "amount": "1",
            "unit": "mg"
          },
          {
            "amount": "10",
            "unit": "ml"
          }
        ]
      },
      {
        "text": "Adrenaline (1:10,000): Formula: 0.01mg/kg Preparation: 1mg in 10mls Dose: 1mg Volume: 10ml",
        "dose_values": [
          {
            "amount": "0.01",
            "unit": "mg"
          },
          {
            "amount": "1",
            "unit": "mg"
          },
          {
            "amount": "1",
            "unit": "mg"
          },
          {
            "amount": "10",
            "unit": "ml"
          }
        ]
      },
      {
        "text": "Adrenaline (1:10,000): Formula: 0.01mg/kg Preparation: 1mg in 10mls Dose: 1mg Volume: 10ml",
        "dose_values": [
          {
            "amount": "0.01",
            "unit": "mg"
          },
          {
            "amount": "1",
            "unit": "mg"
          },
          {
            "amount": "1",
            "unit": "mg"
          },
          {
            "amount": "10",
            "unit": "ml"
          }
        ]
      },
      {
        "text": "Adrenaline (1:10,000): Formula: 0.01mg/kg Preparation: 1mg in 10mls Dose: 1mg Volume: 10ml",
        "dose_values": [
          {
            "amount": "0.01",
            "unit": "mg"
          },
          {
            "amount": "1",
            "unit": "mg"
          },
          {
            "amount": "1",
            "unit": "mg"
          },
          {
            "amount": "10",
            "unit": "ml"
          }
        ]
      },
      {
        "text": "Adrenaline (1:10,000): Formula: 0.01mg/kg Preparation: 1mg in 10mls Dose: 1mg Volume: 10ml",
        "dose_values": [
          {
            "amount": "0.01",
            "unit": "mg"
          },
          {
            "amount": "1",
            "unit": "mg"
          },
          {
            "amount": "1",
            "unit": "mg"
          },
          {
            "amount": "10",
            "unit": "ml"
          }
        ]
      },
      {
        "text": "Adrenaline (1:10,000): Adrenaline (1:10,000): Preparation: 1mg in 10mls Dose: 1mg Volume: 10ml",
        "dose_values": [
          {
            "amount": "1",
            "unit": "mg"
          },
          {
            "amount": "1",
            "unit": "mg"
          },
          {
            "amount": "10",
            "unit": "ml"
          }
        ]
      },
      {
        "text": "Adrenaline (1:10,000): Formula: 0.01mg/kg Preparation: 1mg in 10mls Dose: 1mg Volume: 10ml",
        "dose_values": [
          {
            "amount": "0.01",
            "unit": "mg"
          },
          {
            "amount": "1",
            "unit": "mg"
          },
          {
            "amount": "1",
            "unit": "mg"
          },
          {
            "amount": "10",
            "unit": "ml"
          }
        ]
      },
      {
        "text": "Adrenaline (1:10,000): Formula: 0.01mg/kg Preparation: 1mg in 10mls Dose: 1mg Volume: 10ml",
        "dose_values": [
          {
            "amount": "0.01",
            "unit": "mg"
          },
          {
            "amount": "1",
            "unit": "mg"
          },
          {
            "amount": "1",
            "unit": "mg"
          },
          {
            "amount": "10",
            "unit": "ml"
          }
        ]
      },
      {
        "text": "Adrenaline (1:10,000): Formula: 0.01mg/kg Preparation: 1mg in 10mls Dose: 1mg Volume: 10ml",
        "dose_values": [
          {
            "amount": "0.01",
            "unit": "mg"
          },
          {
            "amount": "1",
            "unit": "mg"
          },
          {
            "amount": "1",
            "unit": "mg"
          },
          {
            "amount": "10",
            "unit": "ml"
          }
        ]
      },
      {
        "text": "Adrenaline (1:10,000): Formula: 0.01mg/kg Preparation: 1mg in 10mls Dose: 1mg Volume: 10ml",
        "dose_values": [
          {
            "amount": "0.01",
            "unit": "mg"
          },
          {
            "amount": "1",
            "unit": "mg"
          },
          {
            "amount": "1",
            "unit": "mg"
          },
          {
            "amount": "10",
            "unit": "ml"
          }
        ]
      },
      {
        "text": "Adrenaline (1:10,000): Formula: 0.01mg/kg Preparation: 1mg in 10mls Dose: 1mg Volume: 10ml",
        "dose_values": [
          {
            "amount": "0.01",
            "unit": "mg"
          },
          {
            "amount": "1",
            "unit": "mg"
          },
          {
            "amount": "1",
            "unit": "mg"
          },
          {
            "amount": "10",
            "unit": "ml"
          }
        ]
      },
      {
        "text": "1mg IV or IO – fast push ",
        "dose_values": [
          {
            "amount": "1",
            "unit": "mg"
          }
        ]
      },
      {
        "text": "IM: 0.01mg/kg (up to 50kg) ",
        "dose_values": [
          {
            "amount": "0.01",
            "unit": "mg"
          }
        ]
      },
      {
        "text": " 0.5mg ",
        "dose_values": [
          {
            "amount": "0.5",
            "unit": "mg"
          }
        ]
      },
      {
        "text": "Weight >10kg: nebulise 5ml adrenaline 1:1,000 Weight <10kg: nebulise 0.5ml/kg adrenaline 1:1,000  Make volume up to 5ml with saline, as required",
        "dose_values": [
          {
            "amount": "5",
            "unit": "ml"
          },
          {
            "amount": "0.5",
            "unit": "ml"
          },
          {
            "amount": "5",
            "unit": "ml"
          }
        ]
      },
      {
        "text": " Add 1mL (1mg) 1:1000 adrenaline to 500mL NaCl.",
        "dose_values": [
          {
            "amount": "1",
            "unit": "mL"
          },
          {
            "amount": "1",
            "unit": "mg"
          },
          {
            "amount": "500",
            "unit": "mL"
          }
        ]
      },
      {
        "text": "Adult (≥40kg) Adrenaline infusion (infusion pump)",
        "dose_values": []
      },
      {
        "text": " Withdraw 3mL from 50mL NaCl bag, then add 3mL (3mg) 1:1000 adrenaline to make 3mg/50mL",
        "dose_values": [
          {
            "amount": "3",
            "unit": "mL"
          },
          {
            "amount": "50",
            "unit": "mL"
          },
          {
            "amount": "3",
            "unit": "mL"
          },
          {
            "amount": "3",
            "unit": "mg"
          },
          {
            "amount": "3",
            "unit": "mg"
          },
          {
            "amount": "50",
            "unit": "mL"
          }
        ]
      },
      {
        "text": "Default bolus: 12mcg (0.2mL)  Lower soft bolus limit: 1.2mcg (0.02mL) Upper soft bolus limit: 24mcg (0.4mL) Upper hard bolus limit: 48mcg (0.8mL) Large Paediatric (21-39kg) Adrenaline infusion (infusion pump)",
        "dose_values": [
          {
            "amount": "12",
            "unit": "mcg"
          },
          {
            "amount": "0.2",
            "unit": "mL"
          },
          {
            "amount": "1.2",
            "unit": "mcg"
          },
          {
            "amount": "0.02",
            "unit": "mL"
          },
          {
            "amount": "24",
            "unit": "mcg"
          },
          {
            "amount": "0.4",
            "unit": "mL"
          },
          {
            "amount": "48",
            "unit": "mcg"
          },
          {
            "amount": "0.8",
            "unit": "mL"
          }
        ]
      },
      {
        "text": " Withdraw 3mL from 50mL NaCl bag, then add 3mL (3mg) 1:1000 adrenaline to make 3mg/50mL",
        "dose_values": [
          {
            "amount": "3",
            "unit": "mL"
          },
          {
            "amount": "50",
            "unit": "mL"
          },
          {
            "amount": "3",
            "unit": "mL"
          },
          {
            "amount": "3",
            "unit": "mg"
          },
          {
            "amount": "3",
            "unit": "mg"
          },
          {
            "amount": "50",
            "unit": "mL"
          }
        ]
      },
      {
        "text": "Default bolus: 6mcg (0.1mL)  Lower soft bolus limit: 0.6mcg (0.01mL) Upper soft bolus limit: 12mcg (0.2mL) Upper hard bolus limit: 48mcg (0.8mL) Small Paediatric (≤20kg) Adrenaline infusion (infusion pump)",
        "dose_values": [
          {
            "amount": "6",
            "unit": "mcg"
          },
          {
            "amount": "0.1",
            "unit": "mL"
          },
          {
            "amount": "0.6",
            "unit": "mcg"
          },
          {
            "amount": "0.01",
            "unit": "mL"
          },
          {
            "amount": "12",
            "unit": "mcg"
          },
          {
            "amount": "0.2",
            "unit": "mL"
          },
          {
            "amount": "48",
            "unit": "mcg"
          },
          {
            "amount": "0.8",
            "unit": "mL"
          }
        ]
      },
      {
        "text": " Withdraw 3mL from 50mL NaCl bag, then add 3mL (300mcg) 1:10,000 adrenaline to make 300mcg/50mL",
        "dose_values": [
          {
            "amount": "3",
            "unit": "mL"
          },
          {
            "amount": "50",
            "unit": "mL"
          },
          {
            "amount": "3",
            "unit": "mL"
          },
          {
            "amount": "300",
            "unit": "mcg"
          },
          {
            "amount": "300",
            "unit": "mcg"
          },
          {
            "amount": "50",
            "unit": "mL"
          }
        ]
      },
      {
        "text": "Adrenaline 0.01mg/kg ",
        "dose_values": [
          {
            "amount": "0.01",
            "unit": "mg"
          }
        ]
      },
      {
        "text": "Adrenaline 0.01mg/kg",
        "dose_values": [
          {
            "amount": "0.01",
            "unit": "mg"
          }
        ]
      },
      {
        "text": " 1mg after 2",
        "dose_values": [
          {
            "amount": "1",
            "unit": "mg"
          }
        ]
      },
      {
        "text": " 1mg immediately (then in every second loop)",
        "dose_values": [
          {
            "amount": "1",
            "unit": "mg"
          }
        ]
      },
      {
        "text": "No more than 3 doses of adrenaline.",
        "dose_values": []
      },
      {
        "text": " 0.01mg/kg",
        "dose_values": [
          {
            "amount": "0.01",
            "unit": "mg"
          }
        ]
      },
      {
        "text": " 0.02mg/kg Repeat adrenaline every 3 minutes while heart rate remains < 60/minute despite effective ventilations and chest compressions.",
        "dose_values": [
          {
            "amount": "0.02",
            "unit": "mg"
          }
        ]
      },
      {
        "text": "Aggressive fluid therapy up to sBP of 90mmHg, maintenance fluid thereafter (max 20ml/kg). ",
        "dose_values": [
          {
            "amount": "20",
            "unit": "ml"
          }
        ]
      },
      {
        "text": " Adrenaline infusion if critically unwell or refractory shock post 20ml/kg fluid. ",
        "dose_values": [
          {
            "amount": "20",
            "unit": "ml"
          }
        ]
      },
      {
        "text": " Adrenaline infusion to maintain sBP of ≥ 90mmHg ICP.",
        "dose_values": []
      },
      {
        "text": " Consider adrenaline infusion if sBP < 90mmHg with clinical signs of shock, refractory to fluids.",
        "dose_values": []
      },
      {
        "text": " Adrenaline infusion if sBP < 90mmHg with clinical signs of shock. ",
        "dose_values": []
      },
      {
        "text": "200mg tablet  100mg/5ml liquid ",
        "dose_values": [
          {
            "amount": "200",
            "unit": "mg"
          },
          {
            "amount": "100",
            "unit": "mg"
          },
          {
            "amount": "5",
            "unit": "ml"
          }
        ]
      },
      {
        "text": "1mMol/kg IV or IO ",
        "dose_values": [
          {
            "amount": "1",
            "unit": "mMol"
          }
        ]
      },
      {
        "text": "1mg of adrenaline into a 500ml",
        "dose_values": [
          {
            "amount": "1",
            "unit": "mg"
          },
          {
            "amount": "500",
            "unit": "ml"
          }
        ]
      },
      {
        "text": "A “LO” or “HI” reading indicates a BGL <1.1mmol /L or >27.8 mmol/L.",
        "dose_values": [
          {
            "amount": "1.1",
            "unit": "mmol"
          },
          {
            "amount": "27.8",
            "unit": "mmol"
          }
        ]
      },
      {
        "text": "##### Type\nA naturally occurring catecholamine [S3]\n\n##### Presentations\n1:10,000 – 1mg in 10ml – glass ampoule \n 1:1,000 – 1mg in 1ml – glass ampoule \n\n##### Actions\n\n- \\u03b1 effect: peripheral vasoconstriction\n\n- \\u03b21 effects: \n\n- increased rate of sinus node\n\n- increased myocardial contractility\n\n- increased AV conduction\n\n- increased myocardial irritability\n\n- \\u03b22 effects: \n\n- bronchodilation\n\n- vasodilation of skeletal muscle\n\nOnset: IV = 30 seconds; IM = 30 – 90 seconds \n Max effect: IV = 3 – 5 min; IM = 4 – 10 mins \n\nEndotracheal use: slightly longer times\n\n#### Uses\n\n- Cardiac arrest\n\n- Anaphylaxis\n\n- Severe life-threatening asthma\n\n- Bradyarrhythmias resistant to atropine **- ICP only**\n\n- Severe upper airway swelling\n\n- Shock unresponsive to fluid boluses **- ICP only**\n\n#### Adverse Effects\n\n- Tachycardia\n\n- Tachyarrhythmias\n\n- Hypertension\n\n#### Contraindications\n\n- Hypovolaemic shock without adequate fluid replacement\n\n#### Precautions\nThese apply to patients with cardiac output only:\n\n- Care with patients with history of hypertension\n\n- Care with patients with history of ischaemic heart disease\n\n- Give extremely slowly to patients on MAO Inhibitor antidepressants (e.g. Nardil, Parnate) as adrenaline may provoke a greatly exaggerated response. Generally, patients on MAOIs with cardiac output should receive no more than \\xbc of the normal dose of adrenaline, titrated to response \n\n- Hypothermia\n\n#### Pregnancy and Breastfeeding##### Pregnancy\n- Safe to use\n\n##### Breastfeeding\n- Safe to use\n\n#### Doses#### Bradyarrhythmias resistant to atropine##### Adult and Paediatric\n- **ICP:** IV/IO adrenaline by infusion – titrated to response\n\n#### Cardiac arrest##### Adult\n- 1mg IV or IO – fast push \n- No limit on number of doses in cardiac arrest.\n\n##### Paediatric\n- IV: 0.01mg/kg – fast push \n- No limit on number of doses in cardiac arrest.\n\n- **ICP:** IO: 0.01mg/kg – fast push \n- No limit on number of doses in cardiac arrest.\n- **ICP:** ETT: NEWBORN ONLY \n- If no IV or IO access – 0.02mg/kg.\n\n#### Anaphylaxis / asthma (severe life threatening)##### Adult\n- IM: 0.5mg \n- Repeat 5 minutely (max three doses).\n\n- **ICP:** If required – **IV/IO** adrenaline by infusion \n- Titrated to response.\n##### Paediatric\n- IM: 0.01mg/kg (up to 50kg) \n- Repeat 5 minutely (max three doses).\n\n- **ICP:** If required – **IV/IO** adrenaline by infusion \n- Titrated to response.\n\n#### Severe upper airway swelling##### Adult\n- **IM:** 0.5mg \n- Repeat 5 minutely (max three doses).\n\n##### Paediatric\n- Weight >10kg: nebulise 5ml adrenaline 1:1,000\n- Weight",
        "dose_values": [
          {
            "amount": "1",
            "unit": "mg"
          },
          {
            "amount": "10",
            "unit": "ml"
          },
          {
            "amount": "1",
            "unit": "mg"
          },
          {
            "amount": "1",
            "unit": "ml"
          },
          {
            "amount": "1",
            "unit": "mg"
          },
          {
            "amount": "0.01",
            "unit": "mg"
          },
          {
            "amount": "0.01",
            "unit": "mg"
          },
          {
            "amount": "0.02",
            "unit": "mg"
          },
          {
            "amount": "0.5",
            "unit": "mg"
          },
          {
            "amount": "0.01",
            "unit": "mg"
          },
          {
            "amount": "0.5",
            "unit": "mg"
          },
          {
            "amount": "5",
            "unit": "ml"
          }
        ],
        "source": "app-adrenaline"
      },
      {
        "text": "#### Indications\n- Patients requiring an adrenaline infusion.\n\n#### Procedure\n\n- Medication checks are to be done by two officers prior to administration.\n\n- Adhere to all aseptic techniques.\n\n- Inject **1mg of adrenaline into a 500ml** bag of saline via the access port.\n\n- Fill out and attach an additive label to the fluid bag.\n\n- Connect a giving set or a burette to the fluid bag. \n- **If you are using a giving set:** ensure the gate clamps are turned off prior to inserting into the fluid bag.\n- **If you are using a burette:** connect a giving set to the bottom of the burette and ensure all gate clamps are turned off prior to inserting into the fluid bag. Now open the ventilation port then the gate clamp and fill the burette to the 100ml mark. Open the gate clamp and prime the line and then refill the burette to the 100ml mark.\n\n- Connect the giving set to the patient and commence infusion. \n- 20 drops/minute = 1ml per minute or 2 mcg/minute\n- Titrate for a response.\n\n- Reassess respiratory and perfusion status.\n\n#### Contraindications\n- Nil when indicated.\n\n#### Specific Notes\n- Ensure that all of the delivery lines are primed with adrenaline. Failure to do this will result in a in a significant delay in the patient receiving adrenaline.\n- If the adrenaline infusion is running through an IO line, you may require a pump set rather than a giving set to overcome increased intra medullar pressure.",
        "dose_values": [
          {
            "amount": "1",
            "unit": "mg"
          },
          {
            "amount": "500",
            "unit": "ml"
          },
          {
            "amount": "100",
            "unit": "ml"
          },
          {
            "amount": "100",
            "unit": "ml"
          },
          {
            "amount": "1",
            "unit": "ml"
          },
          {
            "amount": "2",
            "unit": "mcg"
          }
        ],
        "source": "app-adrenaline-infusion"
      }
    ],
    "Fentanyl": [
      {
        "text": "##### Type\nSynthetic narcotic analgesic [S8]\n\n##### Presentations\n100mcg in 2mL (5mcg/0.1mL) glass ampoule\n\n##### Actions\n\n- Precipitates CNS effects by binding to opioid receptors.\n\n##### Pharmacokinetics\nIN\n Onset: ~ 5 minutes\n Max Effect: 5 – 15 minutes\n Duration: ~ 60 minutes\n\n#### Uses\n\n- Analgesic for moderate to severe pain.\n\n- Safe alternative analgesic in patients with known morphine allergy.\n\n#### Adverse Effects\n\n- Reduced conscious state\n\n- Respiratory depression\n\n- Nausea/vomiting\n\n- Bradycardia (rare)\n\n- Rigidity of the diaphragm, intercostals and jaw (rare)\n\n#### Contraindications\n\n- Known allergy or hypersensitivity\n\n- Bilateral bleeding or occluded nostrils\n\n- Age Increased risk of adverse effects. Consider reducing dose. \n\n- Frail or elderly\nIncreased risk of adverse effects. Consider reducing dose. \n\n- Reduced level of consciousness\nPotential difficulty correctly administering via IN route. \n\n#### Pregnancy and Breastfeeding##### Pregnancy\n- Refrain from use if labour suspected. If administered, prepare for neonatal respiratory support and naloxone administration. \n\n##### Breastfeeding\n- May be used in conservative doses. Encourage feeding/expressing prior to administration.\n\n#### Doses#### Analgesia – Intranasal##### Adult and Paediatric\n- 1.5mcg/kg IN, up to 100mcg. \n- Repeat @5/60 intervals as required.\n\n#### Further Information\n- The atomiser dead space is 0.1mL. To account for this, an additional 0.1mL must be drawn up with the first administration. Pragmatically, this is not required when delivering the full 100mcg dose\n- Ideally volume administered should be limited to 0.3mL – 0.5mL per nostril to a maximum of 1mL.\n- Alternate nostrils until total dose has been delivered.\n- Where possible, IN Fentanyl should be used in addition to paracetamol and an NSAID. - All patients receiving Fentanyl should be on continuous monitoring. - Fentanyl should not be administered if the maximum dose of Morphine has already been administered.\n- Antiemetics should only be administered if the patient has nausea / vomiting prior to or post administration of Fentanyl.",
        "dose_values": [
          {
            "amount": "100",
            "unit": "mcg"
          },
          {
            "amount": "2",
            "unit": "mL"
          },
          {
            "amount": "5",
            "unit": "mcg"
          },
          {
            "amount": "0.1",
            "unit": "mL"
          },
          {
            "amount": "1.5",
            "unit": "mcg"
          },
          {
            "amount": "100",
            "unit": "mcg"
          },
          {
            "amount": "0.1",
            "unit": "mL"
          },
          {
            "amount": "0.1",
            "unit": "mL"
          },
          {
            "amount": "100",
            "unit": "mcg"
          },
          {
            "amount": "0.3",
            "unit": "mL"
          },
          {
            "amount": "0.5",
            "unit": "mL"
          },
          {
            "amount": "1",
            "unit": "mL"
          }
        ],
        "source": "app-fentanyl-intra-nasal"
      }
    ]
  },
  "flowchart": null,
  "checksum": "874b5e0bea59307274bc7bed653b26e423341f83f100383a835f6f7ba3771ae9",
  "extraction_metadata": {
    "timestamp": "2026-04-05T12:20:27.854559+00:00",
    "source_type": "csm",
    "agent_version": "2.0",
    "content_flag": null
  }
}